EasyPyGameGUI
